asyncspotify/__init__.py
asyncspotify/album.py
asyncspotify/artist.py
asyncspotify/audioanalysis.py
asyncspotify/audiofeatures.py
asyncspotify/client.py
asyncspotify/device.py
asyncspotify/exceptions.py
asyncspotify/flags.py
asyncspotify/http.py
asyncspotify/image.py
asyncspotify/mixins.py
asyncspotify/object.py
asyncspotify/pager.py
asyncspotify/playing.py
asyncspotify/playlist.py
asyncspotify/scope.py
asyncspotify/track.py
asyncspotify/user.py
asyncspotify/utils.py
asyncspotify/oauth/__init__.py
asyncspotify/oauth/flows.py
asyncspotify/oauth/mixins.py
asyncspotify/oauth/response.py
asyncspotify-0.12.1.dist-info/LICENSE.txt
asyncspotify-0.12.1.dist-info/METADATA
asyncspotify-0.12.1.dist-info/WHEEL
asyncspotify-0.12.1.dist-info/top_level.txt
asyncspotify-0.12.1.dist-info/RECORD
