Metadata-Version: 2.1
Name: asyncspotify
Version: 0.12.1
Summary: Spotify Web API implementation that is fully asynchronous and object-oriented.
Home-page: https://github.com/Run1e/asyncspotify
Author: RUNIE
Author-email: runar-borge@hotmail.com
License: UNKNOWN
Project-URL: Documentation, https://asyncspotify.rtfd.io/
Keywords: spotify async aio asyncio api webapi
Platform: UNKNOWN
Classifier: Programming Language :: Python :: 3
Classifier: License :: OSI Approved :: MIT License
Classifier: Operating System :: OS Independent
Requires-Python: >=3.5.2
Requires-Dist: aiohttp (>=3.6.0)
